{
  "header": {
    "CustomerName": "PAGE 1 ",
    "CustomerCode": "C07023932",
    "PONumber": "9457",
    "DeliveryDate": "05/12/2025",
    "OrderDate": "05/12/2025"
  },
  "rows": [
    {
      "_id": 1,
      "Barcode": "08901745702001",
      "Description": "RKG MUSTARD OIL 200 ML",
      "Tax": "",
      "Qty": "",
      "PU_HT": "",
      "Total_HT": "ZERO 12 60.99 731.88"
    },
    {
      "_id": 2,
      "Barcode": "08901745102009",
      "Description": "RKG CLASSIC PURE GHEE 200M",
      "Tax": "",
      "Qty": "",
      "PU_HT": "",
      "Total_HT": "ZERO 60 119.70 7,182.00"
    },
    {
      "_id": 3,
      "Barcode": "08901745108001",
      "Description": "RKG CLASSIC PURE GHEE 800G JAR",
      "Tax": "",
      "Qty": "",
      "PU_HT": "",
      "Total_HT": "ZERO 36 437.00 15,732.00"
    },
    {
      "_id": 4,
      "Barcode": "08906058541606",
      "Description": "ALAUKIK SANDAL",
      "Tax": "",
      "Qty": "",
      "PU_HT": "",
      "Total_HT": "VAT 60 48.92 2,935.50"
    },
    {
      "_id": 5,
      "Barcode": "08906058548865",
      "Description": "ALAUKIK SANDAL 6 IN 1 POUCH",
      "Tax": "",
      "Qty": "",
      "PU_HT": "",
      "Total_HT": "VAT 60 62.70 3,762.00"
    },
    {
      "_id": 6,
      "Barcode": "08906058543433",
      "Description": "ALAUKIK SANDAL BARCODE",
      "Tax": "",
      "Qty": "",
      "PU_HT": "",
      "Total_HT": "VAT 60 48.92 2,935.50"
    },
    {
      "_id": 7,
      "Barcode": "08906058546854",
      "Description": "ALAUKIK SANDAL CITRONELLA",
      "Tax": "",
      "Qty": "",
      "PU_HT": "",
      "Total_HT": "VAT 60 48.92 2,935.50"
    },
    {
      "_id": 8,
      "Barcode": "08906058543976",
      "Description": "ALAUKIK SANDAL DUTCH ROSE",
      "Tax": "",
      "Qty": "",
      "PU_HT": "",
      "Total_HT": "VAT 60 48.92 2,935.50"
    },
    {
      "_id": 9,
      "Barcode": "08906058544775",
      "Description": "ALAUKIK SANDAL GOLDEN TREEE",
      "Tax": "",
      "Qty": "",
      "PU_HT": "",
      "Total_HT": "VAT 60 48.92 2,935.50"
    },
    {
      "_id": 10,
      "Barcode": "08906058541583",
      "Description": "ALAUKIK SANDAL LAVENDER",
      "Tax": "",
      "Qty": "",
      "PU_HT": "",
      "Total_HT": "VAT 84 48.92 4,109.70"
    },
    {
      "_id": 11,
      "Barcode": "08906058544805",
      "Description": "ALAUKIK SANDAL LITCHI",
      "Tax": "",
      "Qty": "",
      "PU_HT": "",
      "Total_HT": "VAT 60 48.92 2,935.50"
    },
    {
      "_id": 12,
      "Barcode": "08906058543426",
      "Description": "ALAUKIK SANDAL MAHARAJA",
      "Tax": "",
      "Qty": "",
      "PU_HT": "",
      "Total_HT": "VAT 60 48.92 2,935.50"
    },
    {
      "_id": 13,
      "Barcode": "08906058543365",
      "Description": "ALAUKIK SANDAL MUSK",
      "Tax": "",
      "Qty": "",
      "PU_HT": "",
      "Total_HT": "VAT 84 48.92 4,109.70"
    },
    {
      "_id": 14,
      "Barcode": "08906058544041",
      "Description": "ALAUKIK SANDAL MUSK MELON",
      "Tax": "",
      "Qty": "",
      "PU_HT": "",
      "Total_HT": "VAT 84 48.92 4,109.70"
    },
    {
      "_id": 15,
      "Barcode": "08906058545543",
      "Description": "ALAUKIK SANDAL SAFFRON",
      "Tax": "",
      "Qty": "",
      "PU_HT": "",
      "Total_HT": "VAT 60 48.92 2,935.50"
    },
    {
      "_id": 16,
      "Barcode": "08902259060014",
      "Description": "ARTISAN SMUDGE INCENSE PALO SANTO",
      "Tax": "",
      "Qty": "",
      "PU_HT": "",
      "Total_HT": "VAT 36 20.90 752.40"
    },
    {
      "_id": 17,
      "Barcode": "08902259060069",
      "Description": "ARTISAN SMUDGE INCENSE ROSE",
      "Tax": "",
      "Qty": "",
      "PU_HT": "",
      "Total_HT": "VAT 36 20.90 752.40"
    },
    {
      "_id": 18,
      "Barcode": "08902259060045",
      "Description": "ARTISAN SMUDGE INCENSE SANDALWOOD",
      "Tax": "",
      "Qty": "",
      "PU_HT": "",
      "Total_HT": "VAT 60 20.90 1,254.00"
    },
    {
      "_id": 19,
      "Barcode": "08902259000218",
      "Description": "BHARAT VASI INCENSE STICK RECTANGLE",
      "Tax": "",
      "Qty": "",
      "PU_HT": "",
      "Total_HT": "VAT 144 9.50 1,368.00"
    },
    {
      "_id": 20,
      "Barcode": "08901184115899",
      "Description": "BHARAT VASI SANDAL BOX",
      "Tax": "",
      "Qty": "",
      "PU_HT": "",
      "Total_HT": "VAT 36 114.00 4,104.00"
    },
    {
      "_id": 21,
      "Barcode": "08902264000548",
      "Description": "DARSHAN SAPTHAMI 7 IN 1 SANDAL",
      "Tax": "",
      "Qty": "",
      "PU_HT": "",
      "Total_HT": "VAT 120 11.88 1,425.00"
    },
    {
      "_id": 22,
      "Barcode": "08902264031450",
      "Description": "DARSHAN WHITE STONE SANDAL",
      "Tax": "",
      "Qty": "",
      "PU_HT": "",
      "Total_HT": "VAT 60 10.29 617.31"
    },
    {
      "_id": 23,
      "Barcode": "09780201381139",
      "Description": "ICY SANDAL PINK",
      "Tax": "",
      "Qty": "",
      "PU_HT": "",
      "Total_HT": "VAT 60 10.29 617.31"
    },
    {
      "_id": 24,
      "Barcode": "08906037840164",
      "Description": "INCENSE AMRUTH LAVENDER",
      "Tax": "",
      "Qty": "",
      "PU_HT": "",
      "Total_HT": "VAT 576 9.50 5,472.00"
    },
    {
      "_id": 25,
      "Barcode": "08906037840324",
      "Description": "INCENSE AMRUTH ROSE",
      "Tax": "",
      "Qty": "",
      "PU_HT": "",
      "Total_HT": "VAT 576 9.50 5,472.00"
    },
    {
      "_id": 26,
      "Barcode": "08906057520565",
      "Description": "INCENSE FLORISH SUPREME",
      "Tax": "",
      "Qty": "",
      "PU_HT": "",
      "Total_HT": "VAT 96 9.50 912.00"
    },
    {
      "_id": 27,
      "Barcode": "08902259002205",
      "Description": "INCENSE HERBS LARGE",
      "Tax": "",
      "Qty": "",
      "PU_HT": "",
      "Total_HT": "VAT 60 13.06 783.75"
    },
    {
      "_id": 28,
      "Barcode": "08901851300085",
      "Description": "INCENSE NANDINI FLORA",
      "Tax": "",
      "Qty": "",
      "PU_HT": "",
      "Total_HT": "VAT 288 9.50 2,736.00"
    },
    {
      "_id": 29,
      "Barcode": "08904165701012",
      "Description": "INCENSE STICK BHARAT GEET",
      "Tax": "",
      "Qty": "",
      "PU_HT": "",
      "Total_HT": "VAT 120 9.50 1,140.00"
    },
    {
      "_id": 30,
      "Barcode": "06091188300376",
      "Description": "INCENSE STICK BLACK FIRE",
      "Tax": "",
      "Qty": "",
      "PU_HT": "",
      "Total_HT": "VAT 120 10.29 1,234.62"
    },
    {
      "_id": 31,
      "Barcode": "06091188101874",
      "Description": "INCENSE STICK ELIXIR 100G",
      "Tax": "",
      "Qty": "",
      "PU_HT": "",
      "Total_HT": "VAT 60 33.25 1,995.00"
    },
    {
      "_id": 32,
      "Barcode": "06091188101867",
      "Description": "INCENSE STICK LIORA 100G",
      "Tax": "",
      "Qty": "",
      "PU_HT": "",
      "Total_HT": "VAT 60 33.25 1,995.00"
    },
    {
      "_id": 33,
      "Barcode": "08901851101781",
      "Description": "INCENSE STICK MAAHI",
      "Tax": "",
      "Qty": "",
      "PU_HT": "",
      "Total_HT": "VAT 288 9.50 2,736.00"
    },
    {
      "_id": 34,
      "Barcode": "08901184102431",
      "Description": "INCENSE STICK MOMENTS",
      "Tax": "",
      "Qty": "",
      "PU_HT": "",
      "Total_HT": "VAT 360 9.50 3,420.00"
    },
    {
      "_id": 35,
      "Barcode": "06091188101843",
      "Description": "INCENSE STICK ONE&ONLY FLORA BX 25G",
      "Tax": "",
      "Qty": "",
      "PU_HT": "",
      "Total_HT": "VAT 60 21.38 1,282.50"
    },
    {
      "_id": 36,
      "Barcode": "06091188101850",
      "Description": "INCENSE STICK SAIYAARA 100G",
      "Tax": "",
      "Qty": "",
      "PU_HT": "",
      "Total_HT": "VAT 60 33.25 1,995.00"
    },
    {
      "_id": 37,
      "Barcode": "08908004012444",
      "Description": "MADHUBANI MADDIPAL STICK",
      "Tax": "",
      "Qty": "",
      "PU_HT": "",
      "Total_HT": "VAT 12 106.40 1,276.80"
    },
    {
      "_id": 38,
      "Barcode": "08901184120183",
      "Description": "PARIMAL PURE ROSE DHOOP",
      "Tax": "",
      "Qty": "",
      "PU_HT": "",
      "Total_HT": "VAT 12 76.00 912.00"
    },
    {
      "_id": 39,
      "Barcode": "08901184117930",
      "Description": "PARIMAL PURE SANDAL DHOOP",
      "Tax": "",
      "Qty": "",
      "PU_HT": "",
      "Total_HT": "VAT 12 76.00 912.00"
    },
    {
      "_id": 40,
      "Barcode": "08902259025006",
      "Description": "RAJ SANDAL CITRONELLA LARGE 60G",
      "Tax": "",
      "Qty": "",
      "PU_HT": "",
      "Total_HT": "VAT 60 13.30 798.00"
    },
    {
      "_id": 41,
      "Barcode": "08902259004124",
      "Description": "RAJ SANDAL LAVENDER LARGE 60G",
      "Tax": "",
      "Qty": "",
      "PU_HT": "",
      "Total_HT": "VAT 60 13.30 798.00"
    },
    {
      "_id": 42,
      "Barcode": "08902259025013",
      "Description": "RAJ SANDAL MSY SANDALWOOD LARGE 60G",
      "Tax": "",
      "Qty": "",
      "PU_HT": "",
      "Total_HT": "VAT 60 13.30 798.00"
    },
    {
      "_id": 43,
      "Barcode": "08902259060175",
      "Description": "RAJ SANDAL MUSK LARGE 60G",
      "Tax": "",
      "Qty": "",
      "PU_HT": "",
      "Total_HT": "VAT 60 13.30 798.00"
    },
    {
      "_id": 44,
      "Barcode": "08902259025020",
      "Description": "RAJ SANDAL OUDH LARGE 60G",
      "Tax": "",
      "Qty": "",
      "PU_HT": "",
      "Total_HT": "VAT 60 13.30 798.00"
    },
    {
      "_id": 45,
      "Barcode": "08906056418511",
      "Description": "REIKI INSENCE STICK GOLDEN 225G",
      "Tax": "",
      "Qty": "",
      "PU_HT": "",
      "Total_HT": "VAT 12 95.00 1,140.00"
    },
    {
      "_id": 46,
      "Barcode": "06091188501711",
      "Description": "REIKI INCENSE STICK",
      "Tax": "",
      "Qty": "",
      "PU_HT": "",
      "Total_HT": "VAT 72 15.44 1,111.50"
    },
    {
      "_id": 47,
      "Barcode": "08906056418542",
      "Description": "REIKI SANDAL CITRONELLA 225G",
      "Tax": "",
      "Qty": "",
      "PU_HT": "",
      "Total_HT": "VAT 18 95.00 1,710.00"
    },
    {
      "_id": 48,
      "Barcode": "08906037731028",
      "Description": "SANDAL BLACK FOREST",
      "Tax": "",
      "Qty": "",
      "PU_HT": "",
      "Total_HT": "VAT 240 10.93 2,622.00"
    },
    {
      "_id": 49,
      "Barcode": "08902264062089",
      "Description": "SANDAL DARSHAN LIFE PATCHOLI",
      "Tax": "",
      "Qty": "",
      "PU_HT": "",
      "Total_HT": "VAT 120 10.29 1,234.62"
    },
    {
      "_id": 50,
      "Barcode": "08902264023097",
      "Description": "SANDAL DARSHAN POUCH PARROT",
      "Tax": "",
      "Qty": "",
      "PU_HT": "",
      "Total_HT": "VAT 288 5.94 1,710.00"
    },
    {
      "_id": 51,
      "Barcode": "08906033071494",
      "Description": "SANDAL FORTUNE",
      "Tax": "",
      "Qty": "",
      "PU_HT": "",
      "Total_HT": "VAT 48 10.29 493.85"
    },
    {
      "_id": 52,
      "Barcode": "08901184126734",
      "Description": "SANDAL PARIMAL CHANDAN",
      "Tax": "",
      "Qty": "",
      "PU_HT": "",
      "Total_HT": "VAT 36 9.50 342.00"
    },
    {
      "_id": 53,
      "Barcode": "08901184126710",
      "Description": "SANDAL PARIMAL CITRONELLA",
      "Tax": "",
      "Qty": "",
      "PU_HT": "",
      "Total_HT": "VAT 36 9.50 342.00"
    },
    {
      "_id": 54,
      "Barcode": "08901184124341",
      "Description": "SANDAL PARIMAL LAVENDER",
      "Tax": "",
      "Qty": "",
      "PU_HT": "",
      "Total_HT": "VAT 48 9.50 456.00"
    },
    {
      "_id": 55,
      "Barcode": "08901184126703",
      "Description": "SANDAL PARIMAL VANILLA",
      "Tax": "",
      "Qty": "",
      "PU_HT": "",
      "Total_HT": "VAT 48 9.50 456.00"
    },
    {
      "_id": 56,
      "Barcode": "08901184119996",
      "Description": "SANDAL PURE ROSE 1BOX",
      "Tax": "",
      "Qty": "",
      "PU_HT": "",
      "Total_HT": "VAT 24 76.00 1,824.00"
    },
    {
      "_id": 57,
      "Barcode": "08906037731172",
      "Description": "SANDAL WHITE FOREST",
      "Tax": "",
      "Qty": "",
      "PU_HT": "",
      "Total_HT": "VAT 432 10.93 4,719.60"
    },
    {
      "_id": 58,
      "Barcode": "08906033071784",
      "Description": "SHAKUNTHALA POUCHES GUNDUMALI",
      "Tax": "",
      "Qty": "",
      "PU_HT": "",
      "Total_HT": "VAT 60 6.65 399.00"
    },
    {
      "_id": 59,
      "Barcode": "06091188101089",
      "Description": "SHAKUNTHALA POUCHES JASMINE",
      "Tax": "",
      "Qty": "",
      "PU_HT": "",
      "Total_HT": "VAT 60 6.65 399.00"
    },
    {
      "_id": 60,
      "Barcode": "06091188101003",
      "Description": "SHAKUNTHALA POUCHES MEDITATION",
      "Tax": "",
      "Qty": "",
      "PU_HT": "",
      "Total_HT": "VAT 60 6.65 399.00"
    },
    {
      "_id": 61,
      "Barcode": "06091188101126",
      "Description": "SHAKUNTHALA POUCHES PEACOCK",
      "Tax": "",
      "Qty": "",
      "PU_HT": "",
      "Total_HT": "VAT 60 6.65 399.00"
    },
    {
      "_id": 62,
      "Barcode": "06091188101027",
      "Description": "SHAKUNTHALA POUCHES RELAXATION",
      "Tax": "",
      "Qty": "",
      "PU_HT": "",
      "Total_HT": "VAT 60 6.65 399.00"
    },
    {
      "_id": 63,
      "Barcode": "08904039109906",
      "Description": "SHAKUNTHALA POUCHES SANDAL",
      "Tax": "",
      "Qty": "",
      "PU_HT": "",
      "Total_HT": "VAT 60 6.65 399.00"
    },
    {
      "_id": 64,
      "Barcode": "06091188101164",
      "Description": "SHAKUNTHALA POUCHES TUBEROSE",
      "Tax": "",
      "Qty": "",
      "PU_HT": "",
      "Total_HT": "VAT 60 6.65 399.00"
    },
    {
      "_id": 65,
      "Barcode": "06091188101324",
      "Description": "VIDHI 7IN1 JUNIOR INCENSE",
      "Tax": "",
      "Qty": "",
      "PU_HT": "",
      "Total_HT": "VAT 360 11.88 4,275.00"
    },
    {
      "_id": 66,
      "Barcode": "08906118122578",
      "Description": "VIJAY PINK DROP SANDAL",
      "Tax": "",
      "Qty": "",
      "PU_HT": "",
      "Total_HT": "VAT 120 9.19 1,102.38"
    },
    {
      "_id": 67,
      "Barcode": "08906118121236",
      "Description": "VIJAY SANDAL GOLDEN ORA 100 G",
      "Tax": "",
      "Qty": "",
      "PU_HT": "",
      "Total_HT": "VAT 80 61.75 4,940.00"
    },
    {
      "_id": 68,
      "Barcode": "08906118121809",
      "Description": "VIJAY SANDAL SILVER STONE 100G",
      "Tax": "",
      "Qty": "",
      "PU_HT": "",
      "Total_HT": "VAT 60 61.75 3,705.00"
    },
    {
      "_id": 69,
      "Barcode": "08904079513947",
      "Description": "ASHIKA LOBAN",
      "Tax": "",
      "Qty": "",
      "PU_HT": "",
      "Total_HT": "VAT 60 67.45 4,047.00"
    },
    {
      "_id": 70,
      "Barcode": "05022496001885",
      "Description": "DABUR ROSE WATER 250ML",
      "Tax": "",
      "Qty": "",
      "PU_HT": "",
      "Total_HT": "VAT 12 55.58 666.90"
    },
    {
      "_id": 71,
      "Barcode": "08906037731004",
      "Description": "FOREST BAHUBALI CUP SHAMBRANI",
      "Tax": "",
      "Qty": "",
      "PU_HT": "",
      "Total_HT": "VAT 120 44.65 5,358.00"
    },
    {
      "_id": 72,
      "Barcode": "08908004383896",
      "Description": "MANGALAM BHIMSENI CAMPHOR JAR 50G",
      "Tax": "",
      "Qty": "",
      "PU_HT": "",
      "Total_HT": "VAT 36 83.60 3,009.60"
    },
    {
      "_id": 73,
      "Barcode": "06091188501667",
      "Description": "MANGALAM CAMPHOR 75G",
      "Tax": "",
      "Qty": "",
      "PU_HT": "",
      "Total_HT": "VAT 60 85.50 5,130.00"
    },
    {
      "_id": 74,
      "Barcode": "06091188101805",
      "Description": "PEACE & POWERFUL REAL ROSE 225G",
      "Tax": "",
      "Qty": "",
      "PU_HT": "",
      "Total_HT": "VAT 24 85.50 2,052.00"
    },
    {
      "_id": 75,
      "Barcode": "06091188101812",
      "Description": "PEACE & POWERFUL SHAMBRANI HOUSE BLESSING*12",
      "Tax": "",
      "Qty": "",
      "PU_HT": "",
      "Total_HT": "VAT 60 42.75 2,565.00"
    },
    {
      "_id": 76,
      "Barcode": "06091188101775",
      "Description": "PEACE & POWERFUL SITARA 225G",
      "Tax": "",
      "Qty": "",
      "PU_HT": "",
      "Total_HT": "VAT 24 85.50 2,052.00"
    },
    {
      "_id": 77,
      "Barcode": "06091188101690",
      "Description": "PEACE & POWERFUL WHITE FEATHER 200G",
      "Tax": "",
      "Qty": "",
      "PU_HT": "",
      "Total_HT": "VAT 24 85.50 2,052.00"
    },
    {
      "_id": 78,
      "Barcode": "06091188500035",
      "Description": "RAPID LE MESSE*5",
      "Tax": "",
      "Qty": "",
      "PU_HT": "",
      "Total_HT": "VAT 60 7.13 427.50"
    },
    {
      "_id": 79,
      "Barcode": "06091188500028",
      "Description": "RAPID NEW CAMPHOR*5",
      "Tax": "",
      "Qty": "",
      "PU_HT": "",
      "Total_HT": "VAT 48 23.75 1,140.00"
    },
    {
      "_id": 80,
      "Barcode": "06091188500042",
      "Description": "RAPID NEW SHAMBRANI*3",
      "Tax": "",
      "Qty": "",
      "PU_HT": "",
      "Total_HT": "VAT 48 11.40 547.20"
    },
    {
      "_id": 81,
      "Barcode": "09555524400153",
      "Description": "RAPID PEACOCK SHAMBRANI/12",
      "Tax": "VAT",
      "Qty": "48",
      "PU_HT": "39.90",
      "Total_HT": "1,915.20"
    },
    {
      "_id": 82,
      "Barcode": "06091188501988",
      "Description": "REIKI ENERGY DHOOP 50G",
      "Tax": "VAT",
      "Qty": "36",
      "PU_HT": "38.00",
      "Total_HT": "1,368.00"
    },
    {
      "_id": 83,
      "Barcode": "08901745502007",
      "Description": "RKG GINGERLY OIL 200 ML JAR",
      "Tax": "ZERO",
      "Qty": "12",
      "PU_HT": "65.55",
      "Total_HT": "786.60"
    },
    {
      "_id": 84,
      "Barcode": "06091188502015",
      "Description": "VIDHI CUP SHAMBRANI*12",
      "Tax": "VAT",
      "Qty": "60",
      "PU_HT": "43.70",
      "Total_HT": "2,622.00"
    },
    {
      "_id": 85,
      "Barcode": "06091188502008",
      "Description": "VIDHI DHOOP STICKS 50 G",
      "Tax": "VAT",
      "Qty": "60",
      "PU_HT": "31.35",
      "Total_HT": "1,881.00"
    },
    {
      "_id": 86,
      "Barcode": "06091188701982",
      "Description": "RAPID PEACOCK CANDLE PCK*25",
      "Tax": "VAT",
      "Qty": "240",
      "PU_HT": "95.00",
      "Total_HT": "22,800.00"
    }
  ]
}